scimotf/__init__.py
scimotf/__main__.py
scimotf/base.py
scimotf/doro.py
scimotf-0.1.3.data/data/LICENSE
scimotf-0.1.3.dist-info/LICENSE
scimotf-0.1.3.dist-info/METADATA
scimotf-0.1.3.dist-info/WHEEL
scimotf-0.1.3.dist-info/entry_points.txt
scimotf-0.1.3.dist-info/top_level.txt
scimotf-0.1.3.dist-info/RECORD
