Metadata-Version: 2.1
Name: scimotf
Version: 0.1.3
Home-page: https://github.com/ArianeMora/scimotf
Author: Ariane Mora
Author-email: ariane.n.mora@gmail.com
License: GPL3
Project-URL: Bug Tracker, https://github.com/ArianeMora/scimotf/issues
Project-URL: Documentation, https://github.com/ArianeMora/scimotf
Project-URL: Source Code, https://github.com/ArianeMora/scimotf
Keywords: motif,TF,transcription-factor
Classifier: Intended Audience :: Science/Research
Classifier: License :: OSI Approved :: GNU General Public License v3 (GPLv3)
Classifier: Natural Language :: English
Classifier: Operating System :: OS Independent
Classifier: Programming Language :: Python :: 3.6
Classifier: Programming Language :: Python :: 3.7
Classifier: Programming Language :: Python :: 3.8
Classifier: Topic :: Scientific/Engineering :: Bio-Informatics
Requires-Python: >=3.6
License-File: LICENSE
Requires-Dist: pandas
Requires-Dist: numpy
Requires-Dist: sciutil (>=1.0.3)
Requires-Dist: statsmodels
Requires-Dist: scipy
Requires-Dist: sciviso
Requires-Dist: wordcloud
